chisel3_jar/__init__.py
chisel3_jar/main.py
chisel3_jar/version.py
chisel3_jar/jars/chisel3.jar
chisel3_jar-0.2.dist-info/METADATA
chisel3_jar-0.2.dist-info/WHEEL
chisel3_jar-0.2.dist-info/entry_points.txt
chisel3_jar-0.2.dist-info/top_level.txt
chisel3_jar-0.2.dist-info/RECORD
