Metadata-Version: 2.1
Name: chisel3-jar
Version: 0.2
Summary: Chisel3 Jar is a fat JAR with all of its dependencies.
Home-page: https://github.com/jlsemi
Author: Leway Colin@JLSemi
Author-email: colinlin@jlsemi.com
License: Apache-2.0 License
Keywords: chisel
Platform: UNKNOWN
Requires-Python: >=3.6
